[{"code":"0301420019","name":"Assumption"},{"code":"0301420001","name":"Bagong Buhay I"},{"code":"0301420020","name":"Bagong Buhay II"},{"code":"0301420021","name":"Bagong Buhay III"},{"code":"0301420012","name":"Citrus"},{"code":"0301420022","name":"Ciudad Real"},{"code":"0301420002","name":"Dulong Bayan"},{"code":"0301420015","name":"Fatima I"},{"code":"0301420023","name":"Fatima II"},{"code":"0301420024","name":"Fatima III"},{"code":"0301420025","name":"Fatima IV"},{"code":"0301420026","name":"Fatima V"},{"code":"0301420027","name":"Francisco Homes-Guijo"},{"code":"0301420028","name":"Francisco Homes-Mulawin"},{"code":"0301420029","name":"Francisco Homes-Narra"},{"code":"0301420030","name":"Francisco Homes-Yakal"},{"code":"0301420003","name":"Gaya-gaya"},{"code":"0301420031","name":"Graceville"},{"code":"0301420032","name":"Gumaoc Central"},{"code":"0301420033","name":"Gumaoc East"},{"code":"0301420034","name":"Gumaoc West"},{"code":"0301420005","name":"Kaybanban"},{"code":"0301420004","name":"Kaypian"},{"code":"0301420035","name":"Lawang Pari"},{"code":"0301420036","name":"Maharlika"},{"code":"0301420006","name":"Minuyan I"},{"code":"0301420037","name":"Minuyan II"},{"code":"0301420038","name":"Minuyan III"},{"code":"0301420039","name":"Minuyan IV"},{"code":"0301420041","name":"Minuyan Proper"},{"code":"0301420040","name":"Minuyan V"},{"code":"0301420060","name":"Muzon East"},{"code":"0301420007","name":"Muzon Proper"},{"code":"0301420061","name":"Muzon South"},{"code":"0301420062","name":"Muzon West"},{"code":"0301420042","name":"Paradise III"},{"code":"0301420008","name":"Poblacion"},{"code":"0301420043","name":"Poblacion I"},{"code":"0301420044","name":"San Isidro"},{"code":"0301420045","name":"San Manuel"},{"code":"0301420013","name":"San Martin I"},{"code":"0301420046","name":"San Martin II"},{"code":"0301420047","name":"San Martin III"},{"code":"0301420048","name":"San Martin IV"},{"code":"0301420059","name":"San Martin de Porres"},{"code":"0301420016","name":"San Pedro"},{"code":"0301420049","name":"San Rafael I"},{"code":"0301420017","name":"San Rafael II"},{"code":"0301420050","name":"San Rafael III"},{"code":"0301420051","name":"San Rafael IV"},{"code":"0301420052","name":"San Rafael V"},{"code":"0301420053","name":"San Roque"},{"code":"0301420014","name":"Santa Cruz I"},{"code":"0301420054","name":"Santa Cruz II"},{"code":"0301420055","name":"Santa Cruz III"},{"code":"0301420056","name":"Santa Cruz IV"},{"code":"0301420057","name":"Santa Cruz V"},{"code":"0301420009","name":"Santo Cristo"},{"code":"0301420018","name":"Santo Niño I"},{"code":"0301420058","name":"Santo Niño II"},{"code":"0301420010","name":"Sapang Palay"},{"code":"0301420011","name":"Tungkong Mangga"}]