[{"code":"0401011001","name":"As-Is"},{"code":"0401011002","name":"Balakilong"},{"code":"0401011016","name":"Barangay 1"},{"code":"0401011017","name":"Barangay 2"},{"code":"0401011018","name":"Barangay 3"},{"code":"0401011019","name":"Barangay 4"},{"code":"0401011020","name":"Barangay 5"},{"code":"0401011004","name":"Berinayan"},{"code":"0401011006","name":"Bugaan East"},{"code":"0401011007","name":"Bugaan West"},{"code":"0401011008","name":"Buso-buso"},{"code":"0401011010","name":"Dayap Itaas"},{"code":"0401011011","name":"Gulod"},{"code":"0401011012","name":"J. Leviste"},{"code":"0401011013","name":"Molinete"},{"code":"0401011014","name":"Niyugan"},{"code":"0401011015","name":"Paliparan"},{"code":"0401011021","name":"San Gabriel"},{"code":"0401011022","name":"San Gregorio"},{"code":"0401011023","name":"Santa Maria"},{"code":"0401011024","name":"Ticub"}]