[{"code":"0403411001","name":"Anos"},{"code":"0403411002","name":"Bagong Silang"},{"code":"0403411003","name":"Bambang"},{"code":"0403411004","name":"Batong Malake"},{"code":"0403411005","name":"Baybayin"},{"code":"0403411006","name":"Bayog"},{"code":"0403411007","name":"Lalakay"},{"code":"0403411008","name":"Maahas"},{"code":"0403411015","name":"Malinta"},{"code":"0403411010","name":"Mayondon"},{"code":"0403411011","name":"Putho Tuntungin"},{"code":"0403411012","name":"San Antonio"},{"code":"0403411013","name":"Tadlak"},{"code":"0403411014","name":"Timugan"}]