[{"code":"0405616001","name":"Bacong Ibaba"},{"code":"0405616002","name":"Bacong Ilaya"},{"code":"0405616003","name":"Barangay 1"},{"code":"0405616004","name":"Barangay 2"},{"code":"0405616005","name":"Barangay 3"},{"code":"0405616006","name":"Barangay 4"},{"code":"0405616007","name":"Barangay 5"},{"code":"0405616008","name":"Barangay 6"},{"code":"0405616009","name":"Barangay 7"},{"code":"0405616010","name":"Barangay 8"},{"code":"0405616011","name":"Barangay 9"},{"code":"0405616012","name":"Lavides"},{"code":"0405616013","name":"Magsaysay"},{"code":"0405616014","name":"Malaya"},{"code":"0405616015","name":"Nieva"},{"code":"0405616017","name":"Recto"},{"code":"0405616018","name":"San Ignacio Ibaba"},{"code":"0405616019","name":"San Ignacio Ilaya"},{"code":"0405616020","name":"San Isidro Ibaba"},{"code":"0405616021","name":"San Isidro Ilaya"},{"code":"0405616022","name":"San Jose"},{"code":"0405616023","name":"San Nicolas"},{"code":"0405616024","name":"San Vicente"},{"code":"0405616025","name":"Santa Maria Ibaba"},{"code":"0405616026","name":"Santa Maria Ilaya"},{"code":"0405616027","name":"Sumilang"},{"code":"0405616028","name":"Villarica"}]