[{"code":"0501606012","name":"Anahaw"},{"code":"0501606001","name":"Anameam"},{"code":"0501606002","name":"Awitan"},{"code":"0501606003","name":"Baay"},{"code":"0501606004","name":"Bagacay"},{"code":"0501606005","name":"Bagong Silang I"},{"code":"0501606006","name":"Bagong Silang II"},{"code":"0501606049","name":"Bagong Silang III"},{"code":"0501606007","name":"Bakiad"},{"code":"0501606008","name":"Bautista"},{"code":"0501606009","name":"Bayabas"},{"code":"0501606010","name":"Bayan-bayan"},{"code":"0501606011","name":"Benit"},{"code":"0501606016","name":"Bulhao"},{"code":"0501606017","name":"Cabatuhan"},{"code":"0501606018","name":"Cabusay"},{"code":"0501606019","name":"Calabasa"},{"code":"0501606020","name":"Canapawan"},{"code":"0501606021","name":"Daguit"},{"code":"0501606022","name":"Dalas"},{"code":"0501606023","name":"Dumagmang"},{"code":"0501606024","name":"Exciban"},{"code":"0501606025","name":"Fundado"},{"code":"0501606026","name":"Guinacutan"},{"code":"0501606027","name":"Guisican"},{"code":"0501606013","name":"Gumamela"},{"code":"0501606028","name":"Iberica"},{"code":"0501606015","name":"Kalamunding"},{"code":"0501606030","name":"Lugui"},{"code":"0501606031","name":"Mabilo I"},{"code":"0501606032","name":"Mabilo II"},{"code":"0501606033","name":"Macogon"},{"code":"0501606034","name":"Mahawan-hawan"},{"code":"0501606035","name":"Malangcao-Basud"},{"code":"0501606036","name":"Malasugui"},{"code":"0501606037","name":"Malatap"},{"code":"0501606038","name":"Malaya"},{"code":"0501606039","name":"Malibago"},{"code":"0501606040","name":"Maot"},{"code":"0501606041","name":"Masalong"},{"code":"0501606042","name":"Matanlang"},{"code":"0501606043","name":"Napaod"},{"code":"0501606044","name":"Pag-Asa"},{"code":"0501606045","name":"Pangpang"},{"code":"0501606046","name":"Pinya"},{"code":"0501606047","name":"San Antonio"},{"code":"0501606014","name":"San Francisco"},{"code":"0501606048","name":"Santa Cruz"},{"code":"0501606050","name":"Submakin"},{"code":"0501606051","name":"Talobatib"},{"code":"0501606052","name":"Tigbinan"},{"code":"0501606053","name":"Tulay Na Lupa"}]