[{"code":"0501710001","name":"Baras"},{"code":"0501710002","name":"Del Rosario"},{"code":"0501710003","name":"Dinaga"},{"code":"0501710004","name":"Fundado"},{"code":"0501710005","name":"Haring"},{"code":"0501710006","name":"Iquin"},{"code":"0501710007","name":"Linaga"},{"code":"0501710008","name":"Mangayawan"},{"code":"0501710009","name":"Palo"},{"code":"0501710010","name":"Pangpang"},{"code":"0501710011","name":"Poro"},{"code":"0501710012","name":"San Agustin"},{"code":"0501710014","name":"San Francisco"},{"code":"0501710015","name":"San Jose East"},{"code":"0501710016","name":"San Jose West"},{"code":"0501710017","name":"San Juan"},{"code":"0501710018","name":"San Nicolas"},{"code":"0501710019","name":"San Roque"},{"code":"0501710020","name":"San Vicente"},{"code":"0501710021","name":"Santa Cruz"},{"code":"0501710022","name":"Santa Teresita"},{"code":"0501710023","name":"Sua"},{"code":"0501710024","name":"Talidtid"},{"code":"0501710025","name":"Tibgao"}]