[{"code":"0504102001","name":"Baao"},{"code":"0504102002","name":"Banase"},{"code":"0504102003","name":"Batuila"},{"code":"0504102004","name":"Cagara"},{"code":"0504102005","name":"Cagpandan"},{"code":"0504102006","name":"Cancahorao"},{"code":"0504102007","name":"Canjunday"},{"code":"0504102008","name":"Docol"},{"code":"0504102009","name":"Eastern Capsay"},{"code":"0504102010","name":"Gabi"},{"code":"0504102011","name":"Gangao"},{"code":"0504102012","name":"Lagta"},{"code":"0504102014","name":"Lahong Interior"},{"code":"0504102013","name":"Lahong Proper"},{"code":"0504102015","name":"Lipata"},{"code":"0504102016","name":"Madangcalan"},{"code":"0504102017","name":"Magdalena"},{"code":"0504102018","name":"Manoboc"},{"code":"0504102019","name":"Obongon Diot"},{"code":"0504102020","name":"Poblacion"},{"code":"0504102021","name":"Polot"},{"code":"0504102022","name":"Potoson"},{"code":"0504102023","name":"Sog-Ong"},{"code":"0504102024","name":"Tinapian"}]