[{"code":"0603007001","name":"Acuit"},{"code":"0603007002","name":"Agcuyawan Calsada"},{"code":"0603007003","name":"Agcuyawan Pulo"},{"code":"0603007004","name":"Bagongbong"},{"code":"0603007005","name":"Baras"},{"code":"0603007006","name":"Bungca"},{"code":"0603007007","name":"Cabilauan"},{"code":"0603007008","name":"Cruz"},{"code":"0603007009","name":"Guintas"},{"code":"0603007010","name":"Igbong"},{"code":"0603007011","name":"Ilaud Poblacion"},{"code":"0603007012","name":"Ilaya Poblacion"},{"code":"0603007013","name":"Jalaud"},{"code":"0603007014","name":"Lagubang"},{"code":"0603007015","name":"Lanas"},{"code":"0603007016","name":"Lico-an"},{"code":"0603007017","name":"Linao"},{"code":"0603007018","name":"Monpon"},{"code":"0603007019","name":"Palaciawan"},{"code":"0603007020","name":"Patag"},{"code":"0603007021","name":"Salihid"},{"code":"0603007022","name":"So-ol"},{"code":"0603007023","name":"Sohoton"},{"code":"0603007024","name":"Tabuc-Suba"},{"code":"0603007025","name":"Tabucan"},{"code":"0603007026","name":"Talisay"},{"code":"0603007027","name":"Tinorian"},{"code":"0603007028","name":"Tiwi"},{"code":"0603007029","name":"Tubungan"}]