[{"code":"0802605001","name":"Balagon"},{"code":"0802605018","name":"Barangay 1 Poblacion"},{"code":"0802605019","name":"Barangay 10 Poblacion"},{"code":"0802605020","name":"Barangay 2 Poblacion"},{"code":"0802605021","name":"Barangay 3 Poblacion"},{"code":"0802605022","name":"Barangay 4 Poblacion"},{"code":"0802605023","name":"Barangay 5 Poblacion"},{"code":"0802605024","name":"Barangay 6 Poblacion"},{"code":"0802605025","name":"Barangay 7 Poblacion"},{"code":"0802605026","name":"Barangay 8 Poblacion"},{"code":"0802605027","name":"Barangay 9 Poblacion"},{"code":"0802605002","name":"Baruk"},{"code":"0802605003","name":"Boco"},{"code":"0802605004","name":"Caghalong"},{"code":"0802605005","name":"Camantang"},{"code":"0802605007","name":"Can-ilay"},{"code":"0802605008","name":"Cansangaya"},{"code":"0802605009","name":"Canteros"},{"code":"0802605010","name":"Carolina"},{"code":"0802605011","name":"Guibuangan"},{"code":"0802605012","name":"Jepaco"},{"code":"0802605013","name":"Mabuhay"},{"code":"0802605014","name":"Malogo"},{"code":"0802605015","name":"Obong"},{"code":"0802605016","name":"Pandol"},{"code":"0802605033","name":"Rawis"},{"code":"0802605028","name":"Salvacion"},{"code":"0802605032","name":"Solong"}]