[{"code":"0806414001","name":"Agay-ay"},{"code":"0806414002","name":"Basak"},{"code":"0806414003","name":"Bobon A"},{"code":"0806414018","name":"Bobon B"},{"code":"0806414004","name":"Dayanog"},{"code":"0806414006","name":"Garrido"},{"code":"0806414007","name":"Minoyho"},{"code":"0806414016","name":"Osao"},{"code":"0806414008","name":"Pong-oy"},{"code":"0806414009","name":"San Jose"},{"code":"0806414017","name":"San Roque"},{"code":"0806414010","name":"San Vicente"},{"code":"0806414011","name":"Santa Cruz"},{"code":"0806414005","name":"Santa Filomena"},{"code":"0806414012","name":"Santo Niño"},{"code":"0806414013","name":"Somoje"},{"code":"0806414014","name":"Sua"},{"code":"0806414015","name":"Timba"}]