[{"code":"0906613001","name":"Andalan"},{"code":"0906613002","name":"Bagsak"},{"code":"0906613003","name":"Bandang"},{"code":"0906613004","name":"Bilaan"},{"code":"0906613007","name":"Bud Bunga"},{"code":"0906613008","name":"Buntod"},{"code":"0906613009","name":"Buroh"},{"code":"0906613010","name":"Dalih"},{"code":"0906613011","name":"Gata"},{"code":"0906613059","name":"Kabatuhan Bilaan"},{"code":"0906613014","name":"Kabatuhan Tiis"},{"code":"0906613015","name":"Kabungkol"},{"code":"0906613016","name":"Kagay"},{"code":"0906613017","name":"Kahawa"},{"code":"0906613018","name":"Kandaga"},{"code":"0906613019","name":"Kanlibot"},{"code":"0906613020","name":"Kiutaan"},{"code":"0906613021","name":"Kuhaw"},{"code":"0906613023","name":"Kulamboh"},{"code":"0906613024","name":"Kuttong"},{"code":"0906613025","name":"Lagtoh"},{"code":"0906613026","name":"Lambanah"},{"code":"0906613027","name":"Liban"},{"code":"0906613028","name":"Liu-Bud Pantao"},{"code":"0906613029","name":"Lower Binuang"},{"code":"0906613030","name":"Lower Kamuntayan"},{"code":"0906613031","name":"Lower Laus"},{"code":"0906613032","name":"Lower Sinumaan"},{"code":"0906613033","name":"Lower Talipao"},{"code":"0906613035","name":"Lumbayao"},{"code":"0906613036","name":"Lumping Pigih Daho"},{"code":"0906613037","name":"Lungkiaban"},{"code":"0906613038","name":"Mabahay"},{"code":"0906613039","name":"Mahala"},{"code":"0906613040","name":"Mampallam"},{"code":"0906613041","name":"Marsada"},{"code":"0906613042","name":"Mauboh"},{"code":"0906613043","name":"Mungit-mungit"},{"code":"0906613044","name":"Niog-Sangahan"},{"code":"0906613045","name":"Pantao"},{"code":"0906613047","name":"Samak"},{"code":"0906613048","name":"Talipao Proper"},{"code":"0906613049","name":"Tampakan"},{"code":"0906613051","name":"Tiis"},{"code":"0906613052","name":"Tinggah"},{"code":"0906613053","name":"Tubod"},{"code":"0906613054","name":"Tuyang"},{"code":"0906613060","name":"Upper Binuang"},{"code":"0906613055","name":"Upper Kamuntayan"},{"code":"0906613056","name":"Upper Laus"},{"code":"0906613057","name":"Upper Sinumaan"},{"code":"0906613058","name":"Upper Talipao"}]