[{"code":"0907315001","name":"Bag-ong Balamban"},{"code":"0907315002","name":"Bag-ong Dalaguete"},{"code":"0907315004","name":"Boniao"},{"code":"0907315005","name":"Delusom"},{"code":"0907315006","name":"Diwan"},{"code":"0907315007","name":"Guripan"},{"code":"0907315008","name":"Kaangayan"},{"code":"0907315009","name":"Kabuhi"},{"code":"0907315011","name":"Lourmah"},{"code":"0907315012","name":"Lower Salug Daku"},{"code":"0907315013","name":"Lower Santo Niño"},{"code":"0907315015","name":"Malubo"},{"code":"0907315016","name":"Manguiles"},{"code":"0907315003","name":"Marabanan"},{"code":"0907315017","name":"Panagaan"},{"code":"0907315018","name":"Paraiso"},{"code":"0907315019","name":"Pedagan"},{"code":"0907315020","name":"Poblacion"},{"code":"0907315021","name":"Pugwan"},{"code":"0907315022","name":"San Isidro"},{"code":"0907315023","name":"San Jose"},{"code":"0907315024","name":"San Vicente"},{"code":"0907315025","name":"Santa Cruz"},{"code":"0907315014","name":"Sicpao"},{"code":"0907315027","name":"Tuboran"},{"code":"0907315032","name":"Tulan"},{"code":"0907315028","name":"Tumapic"},{"code":"0907315029","name":"Upper Salug Daku"},{"code":"0907315030","name":"Upper Santo Niño"}]