[{"code":"0907215001","name":"Balok"},{"code":"0907215023","name":"Balunokan"},{"code":"0907215003","name":"Datagan"},{"code":"0907215004","name":"Denoyan"},{"code":"0907215005","name":"Diongan"},{"code":"0907215006","name":"Domogok"},{"code":"0907215007","name":"Dumpilas"},{"code":"0907215008","name":"Gonayen"},{"code":"0907215010","name":"Guibo"},{"code":"0907215011","name":"Gunyan"},{"code":"0907215012","name":"Litolet"},{"code":"0907215013","name":"Macasing"},{"code":"0907215014","name":"Mangilay"},{"code":"0907215015","name":"Moyo"},{"code":"0907215024","name":"Muñoz"},{"code":"0907215016","name":"Pange"},{"code":"0907215017","name":"Paranglumba"},{"code":"0907215019","name":"Polayo"},{"code":"0907215020","name":"Sayaw"},{"code":"0907215021","name":"Seriac"},{"code":"0907215022","name":"Siayan Proper"},{"code":"0907215025","name":"Suguilon"}]