[{"code":"0907223012","name":"Bacong"},{"code":"0907223013","name":"Bagong Silang"},{"code":"0907223001","name":"Banganon"},{"code":"0907223014","name":"Bayanihan"},{"code":"0907223015","name":"Buenavista"},{"code":"0907223008","name":"Canupong"},{"code":"0907223002","name":"Cocob"},{"code":"0907223016","name":"Datagan"},{"code":"0907223017","name":"Imelda"},{"code":"0907223032","name":"Immaculada Concepcion"},{"code":"0907223004","name":"La Libertad"},{"code":"0907223018","name":"Loay"},{"code":"0907223033","name":"Lower Lux"},{"code":"0907223005","name":"Lux"},{"code":"0907223019","name":"Malian"},{"code":"0907223009","name":"Mamawan"},{"code":"0907223020","name":"Map"},{"code":"0907223021","name":"Matunoy"},{"code":"0907223022","name":"New Dapitan"},{"code":"0907223006","name":"Panganuran"},{"code":"0907223007","name":"Pitawe"},{"code":"0907223023","name":"Pitogo"},{"code":"0907223003","name":"Poblacion"},{"code":"0907223024","name":"Salvador"},{"code":"0907223025","name":"San Isidro"},{"code":"0907223026","name":"San Juan"},{"code":"0907223027","name":"San Roque"},{"code":"0907223028","name":"San Vicente"},{"code":"0907223029","name":"Santo Niño"},{"code":"0907223030","name":"Sas"},{"code":"0907223010","name":"Sibalic"},{"code":"0907223011","name":"Tipan"},{"code":"0907223031","name":"Upper Gutalac"}]