[{"code":"1004318001","name":"Argayoso"},{"code":"1004318002","name":"Balintad"},{"code":"1004318003","name":"Cabalantian"},{"code":"1004318004","name":"Camanga"},{"code":"1004318005","name":"Digkilaan"},{"code":"1004318006","name":"Mahayahay"},{"code":"1004318007","name":"Pagawan"},{"code":"1004318008","name":"Paniangan"},{"code":"1004318009","name":"Patag"},{"code":"1004318010","name":"Poblacion"},{"code":"1004318011","name":"Punta Silum"},{"code":"1004318012","name":"Tuod"},{"code":"1004318013","name":"Upper Malubog"}]