[{"code":"1206316024","name":"Aflek"},{"code":"1206316017","name":"Afus"},{"code":"1206316001","name":"Basag"},{"code":"1206316025","name":"Datal Bob"},{"code":"1206316026","name":"Desawo"},{"code":"1206316027","name":"Dlanag"},{"code":"1206316002","name":"Edwards"},{"code":"1206316004","name":"Kematu"},{"code":"1206316005","name":"Laconon"},{"code":"1206316014","name":"Lambangan"},{"code":"1206316018","name":"Lambuling"},{"code":"1206316019","name":"Lamhako"},{"code":"1206316008","name":"Lamsalome"},{"code":"1206316028","name":"Lemsnolon"},{"code":"1206316016","name":"Maan"},{"code":"1206316029","name":"Malugong"},{"code":"1206316030","name":"Mongocayo"},{"code":"1206316011","name":"New Dumangas"},{"code":"1206316020","name":"Poblacion"},{"code":"1206316031","name":"Salacafe"},{"code":"1206316012","name":"Sinolon"},{"code":"1206316032","name":"T'bolok"},{"code":"1206316021","name":"Talcon"},{"code":"1206316022","name":"Talufo"},{"code":"1206316023","name":"Tudok"}]