[{"code":"1705910001","name":"Agbaluto"},{"code":"1705910003","name":"Agbudia"},{"code":"1705910004","name":"Agnaga"},{"code":"1705910005","name":"Agnay"},{"code":"1705910006","name":"Agnipa"},{"code":"1705910002","name":"Agpanabat"},{"code":"1705910007","name":"Agtongo"},{"code":"1705910008","name":"Alad"},{"code":"1705910009","name":"Bagacay"},{"code":"1705910025","name":"Barangay I"},{"code":"1705910026","name":"Barangay II"},{"code":"1705910027","name":"Barangay III"},{"code":"1705910028","name":"Barangay IV"},{"code":"1705910010","name":"Cajimos"},{"code":"1705910011","name":"Calabogo"},{"code":"1705910012","name":"Capaclan"},{"code":"1705910023","name":"Cobrador"},{"code":"1705910013","name":"Ginablan"},{"code":"1705910014","name":"Guimpingan"},{"code":"1705910015","name":"Ilauran"},{"code":"1705910016","name":"Lamao"},{"code":"1705910017","name":"Li-o"},{"code":"1705910018","name":"Logbon"},{"code":"1705910020","name":"Lonos"},{"code":"1705910019","name":"Lunas"},{"code":"1705910021","name":"Macalas"},{"code":"1705910022","name":"Mapula"},{"code":"1705910024","name":"Palje"},{"code":"1705910029","name":"Sablayan"},{"code":"1705910030","name":"Sawang"},{"code":"1705910031","name":"Tambac"}]