[{"code":"1804510001","name":"Aguisan"},{"code":"1804510016","name":"Barangay I"},{"code":"1804510017","name":"Barangay II"},{"code":"1804510018","name":"Barangay III"},{"code":"1804510019","name":"Barangay IV"},{"code":"1804510002","name":"Buenavista"},{"code":"1804510003","name":"Cabadiangan"},{"code":"1804510004","name":"Cabanbanan"},{"code":"1804510005","name":"Carabalan"},{"code":"1804510006","name":"Caradio-an"},{"code":"1804510007","name":"Libacao"},{"code":"1804510010","name":"Mahalang"},{"code":"1804510008","name":"Mambagaton"},{"code":"1804510009","name":"Nabali-an"},{"code":"1804510011","name":"San Antonio"},{"code":"1804510012","name":"Sara-et"},{"code":"1804510013","name":"Su-ay"},{"code":"1804510014","name":"Talaban"},{"code":"1804510015","name":"To-oy"}]