[{"code":"1804516001","name":"Ara-al"},{"code":"1804516002","name":"Ayungon"},{"code":"1804516003","name":"Balabag"},{"code":"1804516010","name":"Barangay I"},{"code":"1804516011","name":"Barangay II"},{"code":"1804516012","name":"Barangay III"},{"code":"1804516004","name":"Batuan"},{"code":"1804516006","name":"Cubay"},{"code":"1804516007","name":"Haguimit"},{"code":"1804516008","name":"La Granja"},{"code":"1804516009","name":"Nagasi"},{"code":"1804516005","name":"Roberto S. Benedicto"},{"code":"1804516013","name":"San Miguel"},{"code":"1804516014","name":"Yubo"}]