[{"code":"1804603001","name":"Balayagmanok"},{"code":"1804603002","name":"Banilad"},{"code":"1804603003","name":"Buntis"},{"code":"1804603004","name":"Buntod"},{"code":"1804603005","name":"Calangag"},{"code":"1804603006","name":"Combado"},{"code":"1804603007","name":"Doldol"},{"code":"1804603008","name":"Isugan"},{"code":"1804603009","name":"Liptong"},{"code":"1804603010","name":"Lutao"},{"code":"1804603011","name":"Magsuhot"},{"code":"1804603012","name":"Malabago"},{"code":"1804603013","name":"Mampas"},{"code":"1804603014","name":"North Poblacion"},{"code":"1804603015","name":"Sacsac"},{"code":"1804603016","name":"San Miguel"},{"code":"1804603017","name":"South Poblacion"},{"code":"1804603018","name":"Sulodpan"},{"code":"1804603019","name":"Timbanga"},{"code":"1804603020","name":"Timbao"},{"code":"1804603021","name":"Tubod"},{"code":"1804603022","name":"West Poblacion"}]